flask_exts/__about__.py
flask_exts/__init__.py
flask_exts/commands.py
flask_exts/constants.py
flask_exts/exts.py
flask_exts/proxies.py
flask_exts/signals.py
flask_exts/types.py
flask_exts/admin/__init__.py
flask_exts/admin/actions.py
flask_exts/admin/admin.py
flask_exts/admin/menu.py
flask_exts/admin/row_action.py
flask_exts/admin/view.py
flask_exts/admin/model/__init__.py
flask_exts/admin/model/ajax.py
flask_exts/admin/model/filters.py
flask_exts/admin/model/form.py
flask_exts/admin/model/typefmt.py
flask_exts/admin/model/view.py
flask_exts/admin/sqla/__init__.py
flask_exts/admin/sqla/ajax.py
flask_exts/admin/sqla/filters.py
flask_exts/admin/sqla/form.py
flask_exts/admin/sqla/typefmt.py
flask_exts/admin/sqla/view.py
flask_exts/babel/__init__.py
flask_exts/babel/selector.py
flask_exts/datastore/__init__.py
flask_exts/datastore/sqla/__init__.py
flask_exts/datastore/sqla/orm.py
flask_exts/email/__init__.py
flask_exts/email/base.py
flask_exts/email/reset_password_sender.py
flask_exts/email/sender.py
flask_exts/email/smtp.py
flask_exts/email/verify_email_sender.py
flask_exts/security/__init__.py
flask_exts/security/core.py
flask_exts/security/email_verification.py
flask_exts/security/hasher.py
flask_exts/security/reset_password.py
flask_exts/security/serializer.py
flask_exts/security/two_factor_authentication.py
flask_exts/security/authorizer/__init__.py
flask_exts/security/authorizer/base.py
flask_exts/security/authorizer/casbin_authorizer.py
flask_exts/security/authorizer/sqlalchemy_adapter.py
flask_exts/security/principal/identity.py
flask_exts/security/principal/identity_context.py
flask_exts/security/principal/permission.py
flask_exts/security/principal/principal.py
flask_exts/template/__init__.py
flask_exts/template/base.py
flask_exts/template/funcs.py
flask_exts/template/rules.py
flask_exts/template/fields/__init__.py
flask_exts/template/fields/ajax_select.py
flask_exts/template/fields/datetime.py
flask_exts/template/fields/file.py
flask_exts-0.2.6.dist-info/METADATA
flask_exts-0.2.6.dist-info/WHEEL
flask_exts-0.2.6.dist-info/entry_points.txt
flask_exts-0.2.6.dist-info/licenses/LICENSE.rst
flask_exts-0.2.6.dist-info/RECORD
