Metadata-Version: 2.4
Name: Flask-Exts
Version: 0.2.6
Summary: Flask extensions with admin, SQLAlchemy, babel, forms, fields, widgets, and so on.
Project-URL: Documentation, https://flask-exts.readthedocs.io
Project-URL: Source, https://github.com/ojso/flask-exts
Project-URL: Homepage, https://github.com/ojso/flask-exts
Project-URL: Issues, https://github.com/ojso/flask-exts/issues
Author-email: David Hua <david.dong.hua@gmail.com>
License: MIT License
License-File: LICENSE.rst
Keywords: admin,babel,flask,form,sql,widget
Classifier: Development Status :: 3 - Alpha
Classifier: Environment :: Web Environment
Classifier: Framework :: Flask
Classifier: Intended Audience :: Developers
Classifier: License :: OSI Approved :: MIT License
Classifier: Programming Language :: Python
Classifier: Programming Language :: Python :: 3
Classifier: Programming Language :: Python :: 3.10
Classifier: Programming Language :: Python :: 3.11
Classifier: Topic :: Software Development :: Build Tools
Requires-Python: >=3.10
Requires-Dist: casbin>=1.0
Requires-Dist: flask-babel>=4.0
Requires-Dist: flask-login>=0.6
Requires-Dist: flask-sqlalchemy>=3.0
Requires-Dist: flask>=3.0
Requires-Dist: pillow>=11.0
Requires-Dist: pyjwt>=2.0
Requires-Dist: pyotp>=2.0
Requires-Dist: qrcode>=8.0
Requires-Dist: tablib>=3.0
Requires-Dist: webauthn>=2.0
Requires-Dist: wtforms>=3.0
Provides-Extra: rediscli
Requires-Dist: redis>=4.0.0; extra == 'rediscli'
